nucling/__init__.py
nucling/donkey.py
nucling/snippet/__init__.py
nucling/snippet/base_64.py
nucling/snippet/dict.py
nucling/snippet/html.py
nucling/snippet/is_type.py
nucling/snippet/iter.py
nucling/snippet/json.py
nucling/snippet/jwt.py
nucling/snippet/madness.py
nucling/snippet/map.py
nucling/snippet/parser.py
nucling/snippet/pipelines.py
nucling/snippet/regex.py
nucling/snippet/ssn.py
nucling/snippet/string.py
nucling/snippet/time.py
nucling-1.2.dist-info/METADATA
nucling-1.2.dist-info/RECORD
nucling-1.2.dist-info/WHEEL
nucling-1.2.dist-info/top_level.txt
tests/__init__.py
tests/donkey.py
tests/snippets/__init__.py
tests/snippets/is_type.py
tests/snippets/map.py
tests/snippets/parser.py
tests/snippets/regex.py
tests/snippets/string.py
tests/snippets/time.py
tests/snippets/dict/__init__.py
tests/snippets/dict/keys_to_camelcase.py
tests/snippets/dict/remove_elements.py
tests/snippets/pipeline/__init__.py
tests/snippets/pipeline/manager.py
tests/snippets/pipeline/pipeline.py
